{
  "Changes": [
    {
      "LogName": "Season-idependent Marriage Dialogue",
      "Action": "EditData",
      "Target": "Characters/Dialogue/MarriageDialogueQuinn",
      "Entries": {
        "Rainy_Night_Quinn": "{{i18n:dialogueMarWinter.Rainy_Night_Quinn}}",
        "Indoor_Night_0": "{{i18n:dialogueMarWinter.Indoor_Night_0}}",
        "Indoor_Night_Quinn": "{{i18n:dialogueMarWinter.Indoor_Night_Quinn}}",
        "Outdoor_3": "{{i18n:dialogueMarWinter.Outdoor_3}}",
        "TwoKids_4": "{{i18n:dialogueMarWinter.TwoKids_4}}",
        "Good_0": "{{i18n:dialogueMarWinter.Good_0}}",
        "Good_3": "{{i18n:dialogueMarWinter.Good_3}}",
        "Good_5": "{{i18n:dialogueMarWinter.Good_5}}",
        "Good_6": "{{i18n:dialogueMarWinter.Good_6}}",
        "Good_7": "{{i18n:dialogueMarWinter.Good_7}}",
        "Neutral_0": "{{i18n:dialogueMarWinter.Neutral_0}}",
        "Neutral_1": "{{i18n:dialogueMarWinter.Neutral_1}}",
        "Neutral_2": "{{i18n:dialogueMarWinter.Neutral_2}}",
        "Neutral_3": "{{i18n:dialogueMarWinter.Neutral_3}}",
        "Neutral_4": "{{i18n:dialogueMarWinter.Neutral_4}}",
        "Neutral_5": "{{i18n:dialogueMarWinter.Neutral_5}}",
        "Neutral_6": "{{i18n:dialogueMarWinter.Neutral_6}}",
        "Neutral_7": "{{i18n:dialogueMarWinter.Neutral_7}}",
        "Neutral_8": "{{i18n:dialogueMarWinter.Neutral_8}}",
        "Neutral_9": "{{i18n:dialogueMarWinter.Neutral_9}}",
        "Bad_0": "{{i18n:dialogueMarWinter.Bad_0}}",
        "Bad_1": "{{i18n:dialogueMarWinter.Bad_1}}",
        "Bad_2": "{{i18n:dialogueMarWinter.Bad_2}}",
        "Bad_3": "{{i18n:dialogueMarWinter.Bad_3}}",
        "Bad_4": "{{i18n:dialogueMarWinter.Bad_4}}",
        "Bad_5": "{{i18n:dialogueMarWinter.Bad_5}}",
        "Bad_6": "{{i18n:dialogueMarWinter.Bad_6}}",
        "Bad_7": "{{i18n:dialogueMarWinter.Bad_7}}",
        "Bad_8": "{{i18n:dialogueMarWinter.Bad_8}}",
        "Bad_9": "{{i18n:dialogueMarWinter.Bad_9}}",
        "{{modID}}_quinnmarriagecrisis": "{{i18n:dialogueMarGen.quinnmarriagecrisis}}",
        "eventSeen_{{ModId}}_jojaparsnip": "{{i18n:dialogueMarGen.eventSeen_jojaparsnip}}",
        "eventSeen_{{ModId}}_overwork": "{{i18n:dialogueMarGen.eventSeen_overwork}}",
        "eventSeen_4081148": "{{i18n:dialogueMarGen.eventSeen_4081148}}",
        "eventSeen_{{ModId}}_beachconfession": "{{i18n:dialogueMarGen.eventSeen_beachconfession}}",
        "eventSeen_{{ModId}}_workplacefight": "{{i18n:dialogueMarGen.eventSeen_workplacefight}}",
        "eventSeen_{{ModId}}_saloonfiasco": "{{i18n:dialogueMarGen.eventSeen_saloonfiasco}}",
        "eventSeen_{{ModId}}_beachcomfort": "{{i18n:dialogueMarGen.eventSeen_beachcomfort}}",
        "eventSeen_{{ModId}}_getupfrombed": "{{i18n:dialogueMarGen.eventSeen_getupfrombed}}",
        "eventSeen_{{ModId}}_picnic": "{{i18n:dialogueMarGen.eventSeen__picnic}}",
        "eventSeen_{{ModId}}_next": "{{i18n:dialogueMarGen.eventSeen_next}}",
      }
    },
    //SUMMER
    {
      "Action": "EditData",
      "Target": "Characters/Dialogue/MarriageDialogueQuinn",
      "Entries": {
        "patio_Quinn": "{{i18n:dialogueMarSummer.patio_Quinn}}",
        "spouseRoom_Quinn": "{{i18n:dialogueMarSummer.spouseRoom_Quinn}}",
        "funLeave_Quinn": "{{i18n:dialogueMarSummer.funLeave_Quinn}}",
        "funReturn_Quinn": "{{i18n:dialogueMarSummer.funReturn_Quinn}}",
        "Rainy_Day_0": "{{i18n:dialogueMarSummer.Rainy_Day_0}}",
        "Rainy_Day_1": "{{i18n:dialogueMarSummer.Rainy_Day_1}}",
        "Rainy_Day_2": "{{i18n:dialogueMarSummer.Rainy_Day_2}}",
        "Rainy_Day_3": "{{i18n:dialogueMarSummer.Rainy_Day_3}}",
        "Rainy_Day_4": "{{i18n:dialogueMarSummer.Rainy_Day_4}}",
        "Rainy_Day_Quinn": "{{i18n:dialogueMarSummer.Rainy_Day_Quinn}}",
        "Rainy_Night_0": "{{i18n:dialogueMarSummer.Rainy_Night_0}}",
        "Rainy_Night_1": "{{i18n:dialogueMarSummer.Rainy_Night_1}}",
        "Rainy_Night_2": "{{i18n:dialogueMarSummer.Rainy_Night_2}}",
        "Rainy_Night_3": "{{i18n:dialogueMarSummer.Rainy_Night_3}}",
        "Rainy_Night_4": "{{i18n:dialogueMarSummer.Rainy_Night_4}}",
        "Indoor_Day_0": "{{i18n:dialogueMarSummer.Indoor_Day_0}}",
        "Indoor_Day_1": "{{i18n:dialogueMarSummer.Indoor_Day_1}}",
        "Indoor_Day_Quinn": "{{i18n:dialogueMarSummer.Indoor_Day_Quinn}}",
        "Indoor_Day_3": "{{i18n:dialogueMarSummer.Indoor_Day_3}}",
        "Indoor_Day_4": "{{i18n:dialogueMarSummer.Indoor_Day_4}}",
        "Indoor_Day_2": "{{i18n:dialogueMarSummer.Indoor_Day_2}}",
        "Indoor_Night_1": "{{i18n:dialogueMarSummer.Indoor_Night_1}}",
        "Indoor_Night_2": "{{i18n:dialogueMarSummer.Indoor_Night_2}}",
        "Indoor_Night_3": "{{i18n:dialogueMarSummer.Indoor_Night_3}}",
        "Indoor_Night_4": "{{i18n:dialogueMarSummer.Indoor_Night_4}}",
        "Outdoor_0": "{{i18n:dialogueMarSummer.Outdoor_0}}",
        "Outdoor_1": "{{i18n:dialogueMarSummer.Outdoor_1}}",
        "Outdoor_2": "{{i18n:dialogueMarSummer.Outdoor_2}}",
        "Outdoor_4": "{{i18n:dialogueMarSummer.Outdoor_4}}",
        "OneKid_0": "{{i18n:dialogueMarSummer.OneKid_0}}",
        "OneKid_1": "{{i18n:dialogueMarSummer.OneKid_1}}",
        "OneKid_2": "{{i18n:dialogueMarSummer.OneKid_2}}",
        "OneKid_3": "{{i18n:dialogueMarSummer.OneKid_3}}",
        "OneKid_4": "{{i18n:dialogueMarSummer.OneKid_4}}",
        "TwoKids_0": "{{i18n:dialogueMarSummer.TwoKids_0}}",
        "TwoKids_1": "{{i18n:dialogueMarSummer.TwoKids_1}}",
        "TwoKids_2": "{{i18n:dialogueMarSummer.TwoKids_2}}",
        "TwoKids_3": "{{i18n:dialogueMarSummer.TwoKids_3}}",
        "Good_1": "{{i18n:dialogueMarSummer.Good_1}}",
        "Good_2": "{{i18n:dialogueMarSummer.Good_2}}",
        "Good_4": "{{i18n:dialogueMarSummer.Good_4}}",
        "Good_9": "{{i18n:dialogueMarSummer.Good_9}}",
        "summer_1": "{{i18n:dialogueMarSummer.summer_1}}",
        "summer_10": "{{i18n:dialogueMarSummer.summer_10}}",
        "summer_11": "{{i18n:dialogueMarSummer.summer_11}}",
        "summer_27": "{{i18n:dialogueMarSummer.summer_27}}",
        "Good_8": "{{i18n:dialogueMarSummer.Good_8}}",
      },
      "When": {
        "Season": "summer"
      }
    },
    //fall
    {
      "Action": "EditData",
      "Target": "Characters/Dialogue/MarriageDialogueQuinn",
      "Entries": {
        "patio_Quinn": "{{i18n:dialogueMarFall.patio_Quinn}}",
        "spouseRoom_Quinn": "{{i18n:dialogueMarFall.spouseRoom_Quinn}}",
        "funLeave_Quinn": "{{i18n:dialogueMarFall.funLeave_Quinn}}",
        "funReturn_Quinn": "{{i18n:dialogueMarFall.funReturn_Quinn}}",
        "Rainy_Day_0": "{{i18n:dialogueMarFall.Rainy_Day_0}}",
        "Rainy_Day_1": "{{i18n:dialogueMarFall.Rainy_Day_1}}",
        "Rainy_Day_2": "{{i18n:dialogueMarFall.Rainy_Day_2}}",
        "Rainy_Day_3": "{{i18n:dialogueMarFall.Rainy_Day_3}}",
        "Rainy_Day_4": "{{i18n:dialogueMarFall.Rainy_Day_4}}",
        "Rainy_Day_Quinn": "{{i18n:dialogueMarFall.Rainy_Day_Quinn}}",
        "Rainy_Night_0": "{{i18n:dialogueMarFall.Rainy_Night_0}}",
        "Rainy_Night_1": "{{i18n:dialogueMarFall.Rainy_Night_1}}",
        "Rainy_Night_2": "{{i18n:dialogueMarFall.Rainy_Night_2}}",
        "Rainy_Night_3": "{{i18n:dialogueMarFall.Rainy_Night_3}}",
        "Rainy_Night_4": "{{i18n:dialogueMarFall.Rainy_Night_4}}",
        "Indoor_Day_0": "{{i18n:dialogueMarFall.Indoor_Day_0}}",
        "Indoor_Day_1": "{{i18n:dialogueMarFall.Indoor_Day_1}}",
        "Indoor_Day_Quinn": "{{i18n:dialogueMarFall.Indoor_Day_Quinn}}",
        "Indoor_Day_3": "{{i18n:dialogueMarFall.Indoor_Day_3}}",
        "Indoor_Day_4": "{{i18n:dialogueMarFall.Indoor_Day_4}}",
        "Indoor_Day_2": "{{i18n:dialogueMarFall.Indoor_Day_2}}",
        "Indoor_Night_1": "{{i18n:dialogueMarFall.Indoor_Night_1}}",
        "Indoor_Night_2": "{{i18n:dialogueMarFall.Indoor_Night_2}}",
        "Indoor_Night_3": "{{i18n:dialogueMarFall.Indoor_Night_3 |HusbandOrWife={{HusbandOrWife}}}}",
        "Indoor_Night_4": "{{i18n:dialogueMarFall.Indoor_Night_4}}",
        "Outdoor_0": "{{i18n:dialogueMarFall.Outdoor_0}}",
        "Outdoor_1": "{{i18n:dialogueMarFall.Outdoor_1}}",
        "Outdoor_2": "{{i18n:dialogueMarFall.Outdoor_2}}",
        "Outdoor_4": "{{i18n:dialogueMarFall.Outdoor_4}}",
        "OneKid_0": "{{i18n:dialogueMarFall.OneKid_0}}",
        "OneKid_1": "{{i18n:dialogueMarFall.OneKid_1|modID={{ModID}}}}",
        "OneKid_2": "{{i18n:dialogueMarFall.OneKid_2}}",
        "OneKid_3": "{{i18n:dialogueMarFall.OneKid_3}}",
        "OneKid_4": "{{i18n:dialogueMarFall.OneKid_4}}",
        "TwoKids_0": "{{i18n:dialogueMarFall.TwoKids_0}}",
        "TwoKids_1": "{{i18n:dialogueMarFall.TwoKids_1}}",
        "TwoKids_2": "{{i18n:dialogueMarFall.TwoKids_2}}",
        "TwoKids_3": "{{i18n:dialogueMarFall.TwoKids_3}}",
        "Good_1": "{{i18n:dialogueMarFall.Good_1}}",
        "Good_2": "{{i18n:dialogueMarFall.Good_2}}",
        "Good_4": "{{i18n:dialogueMarFall.Good_4}}",
        "Good_9": "{{i18n:dialogueMarFall.Good_9}}",
        "fall_1": "{{i18n:dialogueMarFall.fall_1}}",
        "fall_28": "{{i18n:dialogueMarFall.fall_28}}",
        "fall_27": "{{i18n:dialogueMarFall.fall_27}}",
        "fall_26": "{{i18n:dialogueMarFall.fall_26}}",
        "fall_16": "{{i18n:dialogueMarFall.fall_16}}",
        "fall_15": "{{i18n:dialogueMarFall.fall_15}}",
      },
      "When": {
        "Season": "fall"
      }
    },
    //winter
    {
      "Action": "EditData",
      "Target": "Characters/Dialogue/MarriageDialogueQuinn",
      "Entries": {
        "patio_Quinn": "{{i18n:dialogueMarWinter.patio_Quinn}}",
        "spouseRoom_Quinn": "{{i18n:dialogueMarWinter.spouseRoom_Quinn}}",
        "funLeave_Quinn": "{{i18n:dialogueMarWinter.funLeave_Quinn}}",
        "funReturn_Quinn": "{{i18n:dialogueMarWinter.funReturn_Quinn}}",
        "Rainy_Day_0": "{{i18n:dialogueMarWinter.Rainy_Day_0}}",
        "Rainy_Day_1": "{{i18n:dialogueMarWinter.Rainy_Day_1}}",
        "Rainy_Day_2": "{{i18n:dialogueMarWinter.Rainy_Day_2}}",
        "Rainy_Day_3": "{{i18n:dialogueMarWinter.Rainy_Day_3}}",
        "Rainy_Day_4": "{{i18n:dialogueMarWinter.Rainy_Day_4}}",
        "Rainy_Day_Quinn": "{{i18n:dialogueMarWinter.Rainy_Day_Quinn}}",
        "Rainy_Night_0": "{{i18n:dialogueMarWinter.Rainy_Night_0}}",
        "Rainy_Night_1": "{{i18n:dialogueMarWinter.Rainy_Night_1}}",
        "Rainy_Night_2": "{{i18n:dialogueMarWinter.Rainy_Night_2}}",
        "Rainy_Night_3": "{{i18n:dialogueMarWinter.Rainy_Night_3}}",
        "Rainy_Night_4": "{{i18n:dialogueMarWinter.Rainy_Night_4}}",
        "Indoor_Day_0": "{{i18n:dialogueMarWinter.Indoor_Day_0}}",
        "Indoor_Day_1": "{{i18n:dialogueMarWinter.Indoor_Day_1}}",
        "Indoor_Day_Quinn": "{{i18n:dialogueMarWinter.Indoor_Day_Quinn}}",
        "Indoor_Day_3": "{{i18n:dialogueMarWinter.Indoor_Day_3}}",
        "Indoor_Day_4": "{{i18n:dialogueMarWinter.Indoor_Day_4}}",
        "Indoor_Day_2": "{{i18n:dialogueMarWinter.Indoor_Day_2}}",
        "Indoor_Night_1": "{{i18n:dialogueMarWinter.Indoor_Night_1}}",
        "Indoor_Night_2": "{{i18n:dialogueMarWinter.Indoor_Night_2}}",
        "Indoor_Night_3": "{{i18n:dialogueMarWinter.Indoor_Night_3}}",
        "Indoor_Night_4": "{{i18n:dialogueMarWinter.Indoor_Night_4}}",
        "Outdoor_0": "{{i18n:dialogueMarWinter.Outdoor_0}}",
        "Outdoor_1": "{{i18n:dialogueMarWinter.Outdoor_1}}",
        "Outdoor_2": "{{i18n:dialogueMarWinter.Outdoor_2}}",
        "Outdoor_4": "{{i18n:dialogueMarWinter.Outdoor_4}}",
        "OneKid_0": "{{i18n:dialogueMarWinter.OneKid_0}}",
        "OneKid_1": "{{i18n:dialogueMarWinter.OneKid_1}}",
        "OneKid_2": "{{i18n:dialogueMarWinter.OneKid_2}}",
        "OneKid_3": "{{i18n:dialogueMarWinter.OneKid_3}}",
        "OneKid_4": "{{i18n:dialogueMarWinter.OneKid_4}}",
        "TwoKids_0": "{{i18n:dialogueMarWinter.TwoKids_0}}",
        "TwoKids_1": "{{i18n:dialogueMarWinter.TwoKids_1}}",
        "TwoKids_2": "{{i18n:dialogueMarWinter.TwoKids_2}}",
        "TwoKids_3": "{{i18n:dialogueMarWinter.TwoKids_3}}",
        "Good_1": "{{i18n:dialogueMarWinter.Good_1}}",
        "Good_2": "{{i18n:dialogueMarWinter.Good_2}}",
        "Good_4": "{{i18n:dialogueMarWinter.Good_4}}",
        "Good_9": "{{i18n:dialogueMarWinter.Good_9}}",
        "winter_1": "{{i18n:dialogueMarWinter.winter_1}}",
        "winter_24": "{{i18n:dialogueMarWinter.winter_24}}",
        "winter_25": "{{i18n:dialogueMarWinter.winter_25}}",
        "winter_11": "{{i18n:dialogueMarWinter.winter_11}}",
        "winter_12": "{{i18n:dialogueMarWinter.winter_12}}",
        "winter_13": "{{i18n:dialogueMarWinter.winter_13}}",
        "winter_7": "{{i18n:dialogueMarWinter.winter_7}}",
        "winter_15": "{{i18n:dialogueMarWinter.winter_15}}",
        "winter_27": "{{i18n:dialogueMarWinter.winter_27}}",
      },
      "When": {
        "Season": "winter"
      }
    },
    //spring
    {
      "Action": "EditData",
      "Target": "Characters/Dialogue/MarriageDialogueQuinn",
      "Entries": {
        "patio_Quinn": "{{i18n:dialogueMarSpring.patio_Quinn}}",
        "spouseRoom_Quinn": "{{i18n:dialogueMarSpring.spouseRoom_Quinn}}",
        "funLeave_Quinn": "{{i18n:dialogueMarSpring.funLeave_Quinn}}",
        "funReturn_Quinn": "{{i18n:dialogueMarSpring.funReturn_Quinn}}",
        "Rainy_Day_0": "{{i18n:dialogueMarSpring.Rainy_Day_0}}",
        "Rainy_Day_1": "{{i18n:dialogueMarSpring.Rainy_Day_1}}",
        "Rainy_Day_2": "{{i18n:dialogueMarSpring.Rainy_Day_2}}",
        "Rainy_Day_3": "{{i18n:dialogueMarSpring.Rainy_Day_3}}",
        "Rainy_Day_4": "{{i18n:dialogueMarSpring.Rainy_Day_4}}",
        "Rainy_Day_Quinn": "{{i18n:dialogueMarSpring.Rainy_Day_Quinn}}",
        "Rainy_Night_0": "{{i18n:dialogueMarSpring.Rainy_Night_0}}",
        "Rainy_Night_1": "{{i18n:dialogueMarSpring.Rainy_Night_1}}",
        "Rainy_Night_2": "{{i18n:dialogueMarSpring.Rainy_Night_2}}",
        "Rainy_Night_3": "{{i18n:dialogueMarSpring.Rainy_Night_3}}",
        "Rainy_Night_4": "{{i18n:dialogueMarSpring.Rainy_Night_4}}",
        "Indoor_Day_0": "{{i18n:dialogueMarSpring.Indoor_Day_0}}",
        "Indoor_Day_1": "{{i18n:dialogueMarSpring.Indoor_Day_1}}",
        "Indoor_Day_Quinn": "{{i18n:dialogueMarSpring.Indoor_Day_Quinn}}",
        "Indoor_Day_3": "{{i18n:dialogueMarSpring.Indoor_Day_3}}",
        "Indoor_Day_4": "{{i18n:dialogueMarSpring.Indoor_Day_4}}",
        "Indoor_Day_2": "{{i18n:dialogueMarSpring.Indoor_Day_2}}",
        "Indoor_Night_1": "{{i18n:dialogueMarSpring.Indoor_Night_1}}",
        "Indoor_Night_2": "{{i18n:dialogueMarSpring.Indoor_Night_2}}",
        "Indoor_Night_3": "{{i18n:dialogueMarSpring.Indoor_Night_3 |HusbandOrWife={{HusbandOrWife}}}}",
        "Indoor_Night_4": "{{i18n:dialogueMarSpring.Indoor_Night_4}}",
        "Outdoor_0": "{{i18n:dialogueMarSpring.Outdoor_0}}",
        "Outdoor_1": "{{i18n:dialogueMarSpring.Outdoor_1}}",
        "Outdoor_2": "{{i18n:dialogueMarSpring.Outdoor_2}}",
        "Outdoor_4": "{{i18n:dialogueMarSpring.Outdoor_4}}",
        "OneKid_0": "{{i18n:dialogueMarSpring.OneKid_0}}",
        "OneKid_1": "{{i18n:dialogueMarSpring.OneKid_1|modID={{ModID}} }}",
        "OneKid_2": "{{i18n:dialogueMarSpring.OneKid_2}}",
        "OneKid_3": "{{i18n:dialogueMarSpring.OneKid_3}}",
        "OneKid_4": "{{i18n:dialogueMarSpring.OneKid_4}}",
        "TwoKids_0": "{{i18n:dialogueMarSpring.TwoKids_0}}",
        "TwoKids_1": "{{i18n:dialogueMarSpring.TwoKids_1}}",
        "TwoKids_2": "{{i18n:dialogueMarSpring.TwoKids_2}}",
        "TwoKids_3": "{{i18n:dialogueMarSpring.TwoKids_3}}",
        "Good_1": "{{i18n:dialogueMarSpring.Good_1}}",
        "Good_2": "{{i18n:dialogueMarSpring.Good_2}}",
        "Good_4": "{{i18n:dialogueMarSpring.Good_4}}",
        "Good_9": "{{i18n:dialogueMarSpring.Good_9}}",
        "spring_1": "{{i18n:dialogueMarSpring.spring_1}}",
        "spring_20": "{{i18n:dialogueMarSpring.spring_20}}",
        "spring_27": "{{i18n:dialogueMarSpring.spring_27}}",
        "spring_13": "{{i18n:dialogueMarSpring.spring_13}}",
        "spring_24": "{{i18n:dialogueMarSpring.spring_24 |PrinceOrPrincess={{PrinceOrPrincess}}}}",
      },
      "When": {
        "Season": "spring"
      }
    },
    {
      "LogName": "Not Summer Good 8 Marriage Dialogue",
      "Action": "EditData",
      "Target": "Characters/Dialogue/MarriageDialogueQuinn",
      "Entries": {
        "Good_8": "{{i18n:dialogueMar.Good_8}}"
      },
      "When": {
        "Season": "Spring, Fall, Winter"
      }
    }
  ]
}